{
    "Path" : ".\\Bin\\AMD-sgminerHSR\\sgminer.exe",
    "ExtractionPath" : ".\\Bin\\AMD-sgminerHSR\\",
    "Uri" : "https://github.com/Partiolainen/sgminer-gm/releases/download/5.5.5-part/sgminer-5.5.5-part-hsr.win.x64.zip",
    "Types" : ["AMD"],
    "Arguments" : "--api-listen --api-port #APIPORT# -o #PROTOCOL#://#SERVER#:#PORT# -u #LOGIN# -p #PASSWORD# --gpu-platform #GPUPLATFORM# #ALGORITHMPARAMETERS#",
    "API" : "Xgminer",
    "Wrap" : false,
    "Dualmining":false,
    "PrelaunchCommand":"",
    "Algorithms": [
        {"hsr":"-k hsr -I 20"}
    ]
}
