{
    "Path" : ".\\Bin\\cpuminer-opt-4ward\\cpuminer-opt-3.7.6-4ward\\cpuminer-4way.exe",
    "ExtractionPath" : ".\\Bin\\cpuminer-opt-4ward\\",
    "Uri" : "https://github.com/yuzi-co/miners/releases/download/1/cpuminer-opt-3.7.6-4ward.7z",
    "Types" : ["CPU"],
    "Arguments" : "-b #APIPORT# -o #PROTOCOL#://#SERVER#:#PORT# -u #LOGIN# -p #PASSWORD# #ALGORITHMPARAMETERS#",
    "BenchmarkArg": "--benchmark",
    "API" : "Ccminer",
    "Wrap" : false,
    "Dualmining":false,
    "PrelaunchCommand":"",
    "Algorithms": [
        {"skein": "-a skein"},
        {"keccak": "-a keccak"},
        {"keccakc": "-a keccakc"},
        {"nist5": "-a nist5"},
        {"tribus": "-a tribus"},

        {"skein2": "-a skein2"},
        {"jha": "-a jha"},
        {"whirlpool": "-a whirlpool"},
        {"pentablake": "-a pentablake"},

        {"blake": "-a blake"},
        {"lyra2z": "-a lyra2z"},
        {"blake14r": "-a decred"}
    ]
}